{
    "functionName": "test_reverse_sorted",
    "className": "TestMMFlatViews",
    "fileName": "/Axiologue_&_DjangoRestMultipleModels/tests_&_test_flat_view.py",
    "projectName": "repos",
    "Label": false,
    "isTest": true,
    "Body": "\"\"\"\n        Adding a '-' to the front of the sorting_field attribute should order the\n        flat items in reverse\n        \"\"\"\nview = ReversedFlatView.as_view()\nrequest = factory.get('/')\nwith self.assertNumQueries(2):\n    response = view(request).render()\nself.assertEqual(len(response.data), 6)\nself.assertEqual(response.data, list(reversed(self.sorted_results)))\n"
}