{
    "functionName": "test_googlenet_v1_slim",
    "className": "TestModels",
    "fileName": "/Microsoft_&_MMdnn/mmdnn_&_conversion_&_examples_&_coreml_&_test_tfcoreml.py",
    "projectName": "repos",
    "Label": false,
    "isTest": true,
    "Body": "url = (\n    'https://storage.googleapis.com/download.tensorflow.org/models/inception_v1_2016_08_28_frozen.pb.tar.gz'\n    )\ntf_model_dir = _download_file(url=url)\ntf_model_path = os.path.join(TMP_MODEL_DIR, 'inception_v1_2016_08_28_frozen.pb'\n    )\nmlmodel_path = os.path.join(TMP_MODEL_DIR,\n    'inception_v1_2016_08_28_frozen.mlmodel')\nmlmodel = tf_converter.convert(tf_model_path=tf_model_path, mlmodel_path=\n    mlmodel_path, output_feature_names=[\n    'InceptionV1/Logits/Predictions/Softmax:0'], input_name_shape_dict={\n    'input:0': [1, 244, 224, 3]}, image_input_names=['input:0'], red_bias=-\n    1, green_bias=-1, blue_bias=-1, image_scale=2.0 / 255.0)\nself._test_coreml_model_image_input(tf_model_path=tf_model_path,\n    coreml_model=mlmodel, input_tensor_name='input:0', output_tensor_name=\n    'InceptionV1/Logits/Predictions/Softmax:0', img_size=224)\n"
}