{
    "functionName": "test_rfc1123_datetime_inclusive",
    "className": "TestDates",
    "fileName": "/cbefus_&_Eynnyd/tests_&_utils_&_cookies_&_test_rfc.py",
    "projectName": "repos",
    "Label": false,
    "isTest": true,
    "Body": "expression = re.compile(rfc._RFC1123_DATETIME_REGEX)\ngood_examples = ['Mon, 31 Oct 1982 03:21:45 GMT',\n    'Thu, 01 Feb 2045 20:34:22 GMT']\nfor good_example in good_examples:\n    self.assertTrue(bool(expression.fullmatch(good_example)), msg=\n        \"Good rfc1123 datetime '{d}' didn't match regex\".format(d=good_example)\n        )\n"
}