{
    "functionName": "test_properties_2",
    "className": null,
    "fileName": "/mworion_&_MountWizzard4/mw4_&_test_&_unit_tests_&_astrometry_&_test_astrometry.py",
    "projectName": "repos",
    "Label": false,
    "isTest": true,
    "Body": "app.framework = 'astap'\napp.host = 'localhost', 7624\napp.apiKey = 'test'\napp.indexPath = 'test'\napp.name = 'test'\napp.timeout = 30\napp.searchRadius = 20\nassert app.host == ('localhost', 7624)\nassert app.apiKey == 'test'\nassert app.indexPath == 'test'\nassert app.name == 'test'\nassert app.timeout == 30\nassert app.searchRadius == 20\n"
}