{
    "functionName": "parse_pkt",
    "className": null,
    "fileName": "/FaradayRF_&_Faraday-Software/Applications_&_Data_&_client_programs_&_msg_rx.py",
    "projectName": "repos",
    "Label": false,
    "isTest": false,
    "Body": "\"\"\"\n    This function parses the raw packet argument using the expected DATA packet fragment fields.\n\n    :param rx_packet: Received packet to be parsed into fields\n\n    :Return: The parsed packet as a list of fields.\n    \"\"\"\nparsed_data = packet_msg_struct.unpack(rx_packet)\nreturn parsed_data\n"
}