{
    "functionName": "test_quit",
    "className": null,
    "fileName": "/SimLeek_&_CV_PubSubs/tests_&_window_&_test_window_commands.py",
    "projectName": "repos",
    "Label": false,
    "isTest": true,
    "Body": "with mock.patch.object(win_com.win_cmd_pub, 'publish') as mock_pub:\n    win_com.quit()\n    mock_pub.assert_called_once_with('quit', force_all_read=True)\n    mock_pub.reset_mock()\n    win_com.quit(False)\n    mock_pub.assert_called_once_with('quit', force_all_read=False)\n"
}