{
    "functionName": "test_api_categorization_subset_document_id",
    "className": null,
    "fileName": "/FreeDiscovery_&_FreeDiscovery/freediscovery_&_server_&_tests_&_test_categorization.py",
    "projectName": "repos",
    "Label": false,
    "isTest": true,
    "Body": "n_categories = 1\ndsid, lsi_id, _, ds_input = get_features_lsi_cached(app, n_categories=\n    n_categories)\nmethod = V01 + '/feature-extraction/{}'.format(dsid)\ndata = app.get_check(method)\ntraining_set = ds_input['training_set']\npars = {'parent_id': lsi_id, 'data': training_set, 'method': 'NearestNeighbor'}\nmethod = V01 + '/categorization/'\ndata = app.post_check(method, json=pars)\nmid = data['id']\nmethod = V01 + '/categorization/{}/predict'.format(mid)\ndata = app.get_check(method, json={'batch_id': -1, 'subset_document_id': [\n    222784, 5184, 929296, 999999999]})\ndata = data['data']\nassert len(data) == 3\nassert_array_equal([row['document_id'] for row in data], [5184, 222784, 929296]\n    )\nmethod = V01 + '/categorization/{}'.format(mid)\napp.delete_check(method)\n"
}