{
    "functionName": "test_put_twice",
    "className": "test1",
    "fileName": "/jonwright_&_ImageD11/test_&_test_put_incr.py",
    "projectName": "repos",
    "Label": false,
    "isTest": true,
    "Body": "data = np.zeros(10, np.float32)\nind = np.ones(10, np.intp)\nvals = np.ones(10, np.float32)\ncImageD11.put_incr(data, ind, vals)\nassert (data == np.array([0, 10] + [0] * 8, np.float)).all()\ncImageD11.put_incr(data, ind, vals)\nassert (data == np.array([0, 20] + [0] * 8, np.float)).all()\n"
}