{
    "functionName": "test_comparison_on_different_values",
    "className": "TestSplitKey",
    "fileName": "/OpenKMIP_&_PyKMIP/kmip_&_tests_&_unit_&_pie_&_objects_&_test_split_key.py",
    "projectName": "repos",
    "Label": false,
    "isTest": true,
    "Body": "\"\"\"\n        Test that the equality/inequality operators return False/True when\n        comparing two SplitKey objects with different values.\n        \"\"\"\na = objects.SplitKey(key_value=b'\\x00')\nb = objects.SplitKey(key_value=b'\\xff')\nself.assertFalse(a == b)\nself.assertFalse(b == a)\nself.assertTrue(a != b)\nself.assertTrue(b != a)\n"
}