{
    "functionName": "test_compare_several_voltages",
    "className": null,
    "fileName": "/HELMpy_&_HELMpy/test_&_test_compare_several_voltages.py",
    "projectName": "repos",
    "Label": false,
    "isTest": true,
    "Body": "base_profile_csv = (ROOT_PATH / 'data' / 'results' /\n    'Results HELM DS M1 PV1 case118 1.02 1e-08 buses.csv')\ncomparison_csv_list = [ROOT_PATH / 'data' / 'results' /\n    'Results HELM DS M1 PV2 case118 1.02 1e-08 buses.csv', ROOT_PATH /\n    'data' / 'results' /\n    'Results HELM DS M2 PV1 case118 1.02 1e-08 buses.csv', ROOT_PATH /\n    'data' / 'results' / 'Results HELM DS M2 PV2 case118 1.02 1e-08 buses.csv']\nmaximum_voltage_magnitude_difference, maximum_phase_angle_difference = main(\n    base_profile_csv=base_profile_csv, comparison_csv_list=\n    comparison_csv_list, print_all=False)\nassert maximum_voltage_magnitude_difference < 1e-12\nassert maximum_phase_angle_difference < 1e-12\n"
}