{
    "functionName": "test_inline_crossreference",
    "className": "NamespaceTest",
    "fileName": "/whiteclover_&_Choco/test_&_test_namespace.py",
    "projectName": "repos",
    "Label": false,
    "isTest": true,
    "Body": "self._do_memory_test(\n    \"\"\"\n            <%namespace name=\"x\">\n                <%def name=\"a()\">\n                    this is x a\n                </%def>\n                <%def name=\"b()\">\n                    this is x b, and heres ${a()}\n                </%def>\n            </%namespace>\n\n            ${x.a()}\n\n            ${x.b()}\n    \"\"\"\n    , 'this is x a this is x b, and heres this is x a', filters=flatten_result)\n"
}