{
    "functionName": "test_get_headroom",
    "className": "CITestCommon",
    "fileName": "/MichaelMcAleer_&_PyU4V/PyU4V_&_tests_&_ci_tests_&_test_pyu4v_ci_common.py",
    "projectName": "repos",
    "Label": false,
    "isTest": true,
    "Body": "\"\"\"Test get_headroom.\"\"\"\nheadroom_list = self.common.get_headroom(self.conn.array_id)\nself.assertTrue(isinstance(headroom_list, list))\nfor i in range(len(headroom_list)):\n    self.assertTrue(set({'emulation': 'CKD'}.items()).issubset(set(\n        headroom_list[i].items())) or set({'emulation': 'FBA'}.items()).\n        issubset(set(headroom_list[i].items())))\n"
}