{
    "functionName": "test_choose_subset_volumes_no_quotes",
    "className": "TestMigrate",
    "fileName": "/MichaelMcAleer_&_PyU4V/PyU4V_&_tests_&_unit_tests_&_test_migrate.py",
    "projectName": "repos",
    "Label": false,
    "isTest": true,
    "Body": "\"\"\"Test for choose_subset_volumes, no quotes.\"\"\"\nuser_input = '0064F, 0088E, 00890'\nwith mock.patch.object(migrate_utils.MigrateUtils, 'input', return_value=\n    user_input):\n    device_list, create_vol = self.utils.choose_subset_volumes(self.data.\n        smis_sg_1, self.data.device_list)\nself.assertIn('0064F', device_list)\nself.assertIn('0088E', device_list)\nself.assertIn('00890', device_list)\n"
}