{
    "functionName": "createEncryptedContent",
    "className": "TestConsumer",
    "fileName": "/named-data_&_PyNDN2/tests_&_integration_tests_&_test_consumer.py",
    "projectName": "repos",
    "Label": false,
    "isTest": false,
    "Body": "contentData = Data(self.contentName)\nencryptParams = EncryptParams(EncryptAlgorithmType.AesCbc)\nencryptParams.setInitialVector(Blob(INITIAL_VECTOR, False))\nEncryptor.encryptData(contentData, Blob(DATA_CONTENT, False), self.cKeyName,\n    self.fixtureCKeyBlob, encryptParams)\nself.keyChain.sign(contentData, self.certificateName)\nreturn contentData\n"
}