{
    "functionName": "testPamAuth",
    "className": "TestAuthentication",
    "fileName": "/anthill-utils_&_PyMySQL/pymysql_&_tests_&_test_connection.py",
    "projectName": "repos",
    "Label": false,
    "isTest": false,
    "Body": "self.realTestPamAuth()\npytest.mark.skipif(not socket_auth, reason='connection to unix_socket required'\n    )pytest.mark.skipif(not pam_found, reason='no pam plugin')pytest.mark.skipif(os.environ.get('PASSWORD') is None, reason=\n    'PASSWORD env var required')pytest.mark.skipif(os.environ.get('PAMSERVICE') is None, reason=\n    'PAMSERVICE env var required')"
}