{
    "functionName": "test_units",
    "className": "TestMagnitudeUnits",
    "fileName": "/AllenDowney_&_ModSimPy/modsim_&_test_modsim.py",
    "projectName": "repos",
    "Label": false,
    "isTest": true,
    "Body": "x = 5\nres = get_units(x)\nself.assertEqual(res, 1)\nres = get_units(x * UNITS.meter)\nself.assertEqual(res, UNITS.meter)\nt = [1, 2, 3]\nres = get_units(t)\nself.assertEqual(res, [1, 1, 1])\nres = get_units(t * UNITS.meter)\nself.assertEqual(res, UNITS.meter)\ns = ModSimSeries([1, 2, 3])\nres = get_units(s)\nself.assertTrue((res == [1, 1, 1]).all())\nres = get_units(s * UNITS.meter)\nself.assertTrue((res == [UNITS.meter] * 3).all())\nres = get_units(UNITS.meter * s)\nself.assertEqual(res, UNITS.meter)\n"
}