{
    "functionName": "test_equaltiy",
    "className": "AnonymizeResultTest",
    "fileName": "/navikt_&_PyARXaaS/tests_&_pyarxaas_&_models_&_test_AnonymizeResult.py",
    "projectName": "repos",
    "Label": false,
    "isTest": true,
    "Body": "ar1 = AnonymizeResult(self.test_dataset, self.test_risk_profile, self.\n    test_anon_metrics, 'ANONYMOUS')\nar2 = AnonymizeResult(self.test_dataset, self.test_risk_profile, self.\n    test_anon_metrics, 'ANONYMOUS')\nself.assertEqual(ar1, ar2)\nar2._dataset = Dataset([['data', 'data2']])\nself.assertNotEqual(ar1, ar2)\n"
}