{
    "functionName": "test_change_hsv_settings",
    "className": "TestThresholding",
    "fileName": "/MarniTausen_&_Greenotyper/test_sample.py",
    "projectName": "repos",
    "Label": false,
    "isTest": true,
    "Body": "ohue1, ohue2 = self.PL.HSV['hue']\nosat1, osat2 = self.PL.HSV['sat']\noval1, oval2 = self.PL.HSV['val']\nnhue1, nhue2 = 0, 1\nnsat1, nsat2 = 0, 0.8\nnval1, nval2 = 0, 0.6\nself.assertNotEqual(nhue1, ohue1)\nself.assertNotEqual(nhue2, ohue2)\nself.assertNotEqual(nsat1, osat1)\nself.assertNotEqual(nsat2, osat2)\nself.assertNotEqual(nval1, oval1)\nself.assertNotEqual(nval2, oval2)\nself.PL.setHSVmasksettings((nhue1, nhue2), (nsat1, nsat2), (nval1, nval2))\nhue1, hue2 = self.PL.HSV['hue']\nsat1, sat2 = self.PL.HSV['sat']\nval1, val2 = self.PL.HSV['val']\nself.assertEqual(nhue1, hue1)\nself.assertEqual(nhue2, hue2)\nself.assertEqual(nsat1, sat1)\nself.assertEqual(nsat2, sat2)\nself.assertEqual(nval1, val1)\nself.assertEqual(nval2, val2)\n"
}