{
    "functionName": "test_required_settings_defining_types",
    "className": "TestBaseSettingsHandler",
    "fileName": "/David-Lor_&_Python-DotEnv-Settings-Handler/tests_&_test_basesettingshandler.py",
    "projectName": "repos",
    "Label": false,
    "isTest": true,
    "Body": "\"\"\"Test the class with three required parameters: str, int, float.\n        Parameters with types different than str must be converted to their target data type.\n        \"\"\"\nself._write_env(foo='172.17.0.1', bar='6472', baz='123.456')\nclass MySettings(BaseSettingsHandler):\n    foo: str\n    bar: int\n    baz: float\nsettings = MySettings()\nassert settings.foo == '172.17.0.1'\nassert settings.bar == 6472\nassert settings.baz == 123.456\n"
}