{
    "functionName": "test_sklearn_wrapper_transform_with_predict",
    "className": null,
    "fileName": "/Neuraxio_&_Neuraxle/testing_&_steps_&_test_sklearn_wrapper.py",
    "projectName": "repos",
    "Label": false,
    "isTest": true,
    "Body": "p = SKLearnWrapper(LinearRegression())\ndata_inputs = np.expand_dims(np.array(list(range(10))), axis=-1)\nexpected_outputs = np.expand_dims(np.array(list(range(10, 20))), axis=-1)\np = p.fit(data_inputs, expected_outputs)\noutputs = p.transform(data_inputs)\nassert np.array_equal(outputs, expected_outputs)\n"
}