{
    "functionName": "test_agilent34410a_fetch",
    "className": null,
    "fileName": "/Galvant_&_InstrumentKit/instruments_&_tests_&_test_agilent_&_test_agilent_34410a.py",
    "projectName": "repos",
    "Label": false,
    "isTest": true,
    "Body": "with expected_protocol(ik.agilent.Agilent34410a, ['CONF?', 'FETC?'], [\n    'VOLT +1.000000E+01,+3.000000E-06', '+4.27150000E-03,5.27150000E-03']\n    ) as dmm:\n    data = dmm.fetch()\n    unit_eq(data[0], 0.0042715 * u.volt)\n    unit_eq(data[1], 0.0052715 * u.volt)\n"
}