[
  {
    "name": "autodepgraph_\u0026_tests_\u0026_test_graph.py",
    "testCases": [
      {
        "name": "Test_Graph",
        "detectorResults": [
          {
            "name": "AssertionRoulette",
            "hasSmell": true,
            "detail": {
              "assertionCallsInTests": [
                [
                  "test_bad_node",
                  "[PyCallExpression: self.assertEqual, PyCallExpression: self.assertEqual, PyCallExpression: self.assertEqual, PyCallExpression: self.assertRaises, PyCallExpression: self.assertEqual, PyCallExpression: self.assertEqual, PyCallExpression: self.assertEqual]"
                ],
                [
                  "test_write_read_yaml",
                  "[PyCallExpression: self.assertTrue, PyCallExpression: self.assertEqual, PyCallExpression: self.assertEqual]"
                ],
                [
                  "test_calibration_state",
                  "[]"
                ],
                [
                  "test_default_not_implemented_cal",
                  "[PyCallExpression: self.assertEqual, PyCallExpression: self.assertRaises, PyCallExpression: self.assertEqual, PyCallExpression: self.assertRaises]"
                ],
                [
                  "test_tolerance_check",
                  "[PyCallExpression: self.assertEqual, PyCallExpression: self.assertEqual, PyCallExpression: self.assertEqual]"
                ],
                [
                  "test_adding_edge_nonexistent_node",
                  "[PyCallExpression: self.assertRaises, PyCallExpression: self.assertRaises]"
                ],
                [
                  "test_plotting_svg",
                  "[]"
                ],
                [
                  "test_maintain_node_assume_unkown_is_good",
                  "[PyCallExpression: self.assertEqual, PyCallExpression: self.assertEqual]"
                ],
                [
                  "test_maintain_node_require_cal",
                  "[PyCallExpression: self.assertEqual, PyCallExpression: self.assertEqual, PyCallExpression: self.assertEqual]"
                ],
                [
                  "test_plotting_mpl",
                  "[]"
                ],
                [
                  "test_set_function",
                  "[PyCallExpression: self.assertEqual, PyCallExpression: self.assertEqual]"
                ],
                [
                  "test_dummy_cal_three_qubit_graph",
                  "[PyCallExpression: self.assertEqual, PyCallExpression: self.assertEqual]"
                ]
              ],
              "assertStatementsInTests": [
                [
                  "test_bad_node",
                  "[]"
                ],
                [
                  "test_write_read_yaml",
                  "[]"
                ],
                [
                  "test_calibration_state",
                  "[PyAssertStatement]"
                ],
                [
                  "test_default_not_implemented_cal",
                  "[]"
                ],
                [
                  "test_tolerance_check",
                  "[]"
                ],
                [
                  "test_adding_edge_nonexistent_node",
                  "[]"
                ],
                [
                  "test_plotting_svg",
                  "[]"
                ],
                [
                  "test_maintain_node_assume_unkown_is_good",
                  "[]"
                ],
                [
                  "test_maintain_node_require_cal",
                  "[]"
                ],
                [
                  "test_plotting_mpl",
                  "[]"
                ],
                [
                  "test_set_function",
                  "[]"
                ],
                [
                  "test_dummy_cal_three_qubit_graph",
                  "[]"
                ]
              ]
            }
          },
          {
            "name": "ConditionalTestLogic",
            "hasSmell": true,
            "detail": {
              "testHasConditionalTestLogic": [
                [
                  "test_bad_node",
                  "true"
                ],
                [
                  "test_write_read_yaml",
                  "false"
                ],
                [
                  "test_calibration_state",
                  "false"
                ],
                [
                  "test_default_not_implemented_cal",
                  "false"
                ],
                [
                  "test_tolerance_check",
                  "false"
                ],
                [
                  "test_adding_edge_nonexistent_node",
                  "false"
                ],
                [
                  "test_plotting_svg",
                  "false"
                ],
                [
                  "test_maintain_node_assume_unkown_is_good",
                  "false"
                ],
                [
                  "test_maintain_node_require_cal",
                  "false"
                ],
                [
                  "test_plotting_mpl",
                  "false"
                ],
                [
                  "test_set_function",
                  "false"
                ],
                [
                  "test_dummy_cal_three_qubit_graph",
                  "false"
                ]
              ],
              "testHasComprehension": [
                [
                  "test_bad_node",
                  "false"
                ],
                [
                  "test_write_read_yaml",
                  "false"
                ],
                [
                  "test_calibration_state",
                  "false"
                ],
                [
                  "test_default_not_implemented_cal",
                  "false"
                ],
                [
                  "test_tolerance_check",
                  "false"
                ],
                [
                  "test_adding_edge_nonexistent_node",
                  "false"
                ],
                [
                  "test_plotting_svg",
                  "false"
                ],
                [
                  "test_maintain_node_assume_unkown_is_good",
                  "false"
                ],
                [
                  "test_maintain_node_require_cal",
                  "false"
                ],
                [
                  "test_plotting_mpl",
                  "false"
                ],
                [
                  "test_set_function",
                  "false"
                ],
                [
                  "test_dummy_cal_three_qubit_graph",
                  "false"
                ]
              ]
            }
          },
          {
            "name": "ConstructorInitialization",
            "hasSmell": false
          },
          {
            "name": "DefaultTest",
            "hasSmell": false
          },
          {
            "name": "DuplicateAssertion",
            "hasSmell": true,
            "detail": {
              "testHasDuplicateAssertCall": [
                [
                  "test_bad_node",
                  "false"
                ],
                [
                  "test_write_read_yaml",
                  "false"
                ],
                [
                  "test_calibration_state",
                  "false"
                ],
                [
                  "test_default_not_implemented_cal",
                  "true"
                ],
                [
                  "test_tolerance_check",
                  "true"
                ],
                [
                  "test_adding_edge_nonexistent_node",
                  "true"
                ],
                [
                  "test_plotting_svg",
                  "false"
                ],
                [
                  "test_maintain_node_assume_unkown_is_good",
                  "false"
                ],
                [
                  "test_maintain_node_require_cal",
                  "false"
                ],
                [
                  "test_plotting_mpl",
                  "false"
                ],
                [
                  "test_set_function",
                  "false"
                ],
                [
                  "test_dummy_cal_three_qubit_graph",
                  "false"
                ]
              ],
              "testHasDuplicateAssertStatement": [
                [
                  "test_bad_node",
                  "false"
                ],
                [
                  "test_write_read_yaml",
                  "false"
                ],
                [
                  "test_calibration_state",
                  "false"
                ],
                [
                  "test_default_not_implemented_cal",
                  "false"
                ],
                [
                  "test_tolerance_check",
                  "false"
                ],
                [
                  "test_adding_edge_nonexistent_node",
                  "false"
                ],
                [
                  "test_plotting_svg",
                  "false"
                ],
                [
                  "test_maintain_node_assume_unkown_is_good",
                  "false"
                ],
                [
                  "test_maintain_node_require_cal",
                  "false"
                ],
                [
                  "test_plotting_mpl",
                  "false"
                ],
                [
                  "test_set_function",
                  "false"
                ],
                [
                  "test_dummy_cal_three_qubit_graph",
                  "false"
                ]
              ]
            }
          },
          {
            "name": "EmptyTest",
            "hasSmell": false,
            "detail": [
              [
                "test_bad_node",
                "false"
              ],
              [
                "test_write_read_yaml",
                "false"
              ],
              [
                "test_calibration_state",
                "false"
              ],
              [
                "test_default_not_implemented_cal",
                "false"
              ],
              [
                "test_tolerance_check",
                "false"
              ],
              [
                "test_adding_edge_nonexistent_node",
                "false"
              ],
              [
                "test_plotting_svg",
                "false"
              ],
              [
                "test_maintain_node_assume_unkown_is_good",
                "false"
              ],
              [
                "test_maintain_node_require_cal",
                "false"
              ],
              [
                "test_plotting_mpl",
                "false"
              ],
              [
                "test_set_function",
                "false"
              ],
              [
                "test_dummy_cal_three_qubit_graph",
                "false"
              ]
            ]
          },
          {
            "name": "ExceptionHandling",
            "hasSmell": false,
            "detail": [
              [
                "test_bad_node",
                "false"
              ],
              [
                "test_write_read_yaml",
                "false"
              ],
              [
                "test_calibration_state",
                "false"
              ],
              [
                "test_default_not_implemented_cal",
                "false"
              ],
              [
                "test_tolerance_check",
                "false"
              ],
              [
                "test_adding_edge_nonexistent_node",
                "false"
              ],
              [
                "test_plotting_svg",
                "false"
              ],
              [
                "test_maintain_node_assume_unkown_is_good",
                "false"
              ],
              [
                "test_maintain_node_require_cal",
                "false"
              ],
              [
                "test_plotting_mpl",
                "false"
              ],
              [
                "test_set_function",
                "false"
              ],
              [
                "test_dummy_cal_three_qubit_graph",
                "false"
              ]
            ]
          },
          {
            "name": "GeneralFixture",
            "hasSmell": true,
            "detail": [
              [
                "test_bad_node",
                [
                  "self.test_graph"
                ]
              ],
              [
                "test_write_read_yaml",
                []
              ],
              [
                "test_calibration_state",
                []
              ],
              [
                "test_default_not_implemented_cal",
                [
                  "self.test_graph"
                ]
              ],
              [
                "test_tolerance_check",
                []
              ],
              [
                "test_adding_edge_nonexistent_node",
                [
                  "self.test_graph"
                ]
              ],
              [
                "test_plotting_svg",
                []
              ],
              [
                "test_maintain_node_assume_unkown_is_good",
                []
              ],
              [
                "test_maintain_node_require_cal",
                []
              ],
              [
                "test_plotting_mpl",
                []
              ],
              [
                "test_set_function",
                []
              ],
              [
                "test_dummy_cal_three_qubit_graph",
                [
                  "self.test_graph"
                ]
              ]
            ]
          },
          {
            "name": "IgnoredTest",
            "hasSmell": false,
            "detail": [
              [
                "test_bad_node",
                "false"
              ],
              [
                "test_write_read_yaml",
                "false"
              ],
              [
                "test_calibration_state",
                "false"
              ],
              [
                "test_default_not_implemented_cal",
                "false"
              ],
              [
                "test_tolerance_check",
                "false"
              ],
              [
                "test_adding_edge_nonexistent_node",
                "false"
              ],
              [
                "test_plotting_svg",
                "false"
              ],
              [
                "test_maintain_node_assume_unkown_is_good",
                "false"
              ],
              [
                "test_maintain_node_require_cal",
                "false"
              ],
              [
                "test_plotting_mpl",
                "false"
              ],
              [
                "test_set_function",
                "false"
              ],
              [
                "test_dummy_cal_three_qubit_graph",
                "false"
              ]
            ]
          },
          {
            "name": "MagicNumberTest",
            "hasSmell": true,
            "detail": [
              [
                "test_bad_node",
                "false"
              ],
              [
                "test_write_read_yaml",
                "false"
              ],
              [
                "test_calibration_state",
                "false"
              ],
              [
                "test_default_not_implemented_cal",
                "false"
              ],
              [
                "test_tolerance_check",
                "false"
              ],
              [
                "test_adding_edge_nonexistent_node",
                "false"
              ],
              [
                "test_plotting_svg",
                "false"
              ],
              [
                "test_maintain_node_assume_unkown_is_good",
                "false"
              ],
              [
                "test_maintain_node_require_cal",
                "false"
              ],
              [
                "test_plotting_mpl",
                "false"
              ],
              [
                "test_set_function",
                "true"
              ],
              [
                "test_dummy_cal_three_qubit_graph",
                "false"
              ]
            ]
          },
          {
            "name": "RedundantAssertion",
            "hasSmell": false,
            "detail": {
              "testMethodHaveRedundantAssertCall": [
                [
                  "test_bad_node",
                  "0"
                ],
                [
                  "test_write_read_yaml",
                  "0"
                ],
                [
                  "test_calibration_state",
                  "0"
                ],
                [
                  "test_default_not_implemented_cal",
                  "0"
                ],
                [
                  "test_tolerance_check",
                  "0"
                ],
                [
                  "test_adding_edge_nonexistent_node",
                  "0"
                ],
                [
                  "test_plotting_svg",
                  "0"
                ],
                [
                  "test_maintain_node_assume_unkown_is_good",
                  "0"
                ],
                [
                  "test_maintain_node_require_cal",
                  "0"
                ],
                [
                  "test_plotting_mpl",
                  "0"
                ],
                [
                  "test_set_function",
                  "0"
                ],
                [
                  "test_dummy_cal_three_qubit_graph",
                  "0"
                ]
              ],
              "testMethodHaveRedundantAssertStatement": [
                [
                  "test_bad_node",
                  "0"
                ],
                [
                  "test_write_read_yaml",
                  "0"
                ],
                [
                  "test_calibration_state",
                  "0"
                ],
                [
                  "test_default_not_implemented_cal",
                  "0"
                ],
                [
                  "test_tolerance_check",
                  "0"
                ],
                [
                  "test_adding_edge_nonexistent_node",
                  "0"
                ],
                [
                  "test_plotting_svg",
                  "0"
                ],
                [
                  "test_maintain_node_assume_unkown_is_good",
                  "0"
                ],
                [
                  "test_maintain_node_require_cal",
                  "0"
                ],
                [
                  "test_plotting_mpl",
                  "0"
                ],
                [
                  "test_set_function",
                  "0"
                ],
                [
                  "test_dummy_cal_three_qubit_graph",
                  "0"
                ]
              ]
            }
          },
          {
            "name": "RedundantPrint",
            "hasSmell": false,
            "detail": [
              [
                "test_bad_node",
                "false"
              ],
              [
                "test_write_read_yaml",
                "false"
              ],
              [
                "test_calibration_state",
                "false"
              ],
              [
                "test_default_not_implemented_cal",
                "false"
              ],
              [
                "test_tolerance_check",
                "false"
              ],
              [
                "test_adding_edge_nonexistent_node",
                "false"
              ],
              [
                "test_plotting_svg",
                "false"
              ],
              [
                "test_maintain_node_assume_unkown_is_good",
                "false"
              ],
              [
                "test_maintain_node_require_cal",
                "false"
              ],
              [
                "test_plotting_mpl",
                "false"
              ],
              [
                "test_set_function",
                "false"
              ],
              [
                "test_dummy_cal_three_qubit_graph",
                "false"
              ]
            ]
          },
          {
            "name": "SleepyTest",
            "hasSmell": false,
            "detail": [
              [
                "test_bad_node",
                "false"
              ],
              [
                "test_write_read_yaml",
                "false"
              ],
              [
                "test_calibration_state",
                "false"
              ],
              [
                "test_default_not_implemented_cal",
                "false"
              ],
              [
                "test_tolerance_check",
                "false"
              ],
              [
                "test_adding_edge_nonexistent_node",
                "false"
              ],
              [
                "test_plotting_svg",
                "false"
              ],
              [
                "test_maintain_node_assume_unkown_is_good",
                "false"
              ],
              [
                "test_maintain_node_require_cal",
                "false"
              ],
              [
                "test_plotting_mpl",
                "false"
              ],
              [
                "test_set_function",
                "false"
              ],
              [
                "test_dummy_cal_three_qubit_graph",
                "false"
              ]
            ]
          },
          {
            "name": "UnknownTest",
            "hasSmell": true,
            "detail": [
              [
                "test_bad_node",
                "7"
              ],
              [
                "test_write_read_yaml",
                "3"
              ],
              [
                "test_calibration_state",
                "1"
              ],
              [
                "test_default_not_implemented_cal",
                "4"
              ],
              [
                "test_tolerance_check",
                "3"
              ],
              [
                "test_adding_edge_nonexistent_node",
                "2"
              ],
              [
                "test_plotting_svg",
                "0"
              ],
              [
                "test_maintain_node_assume_unkown_is_good",
                "2"
              ],
              [
                "test_maintain_node_require_cal",
                "3"
              ],
              [
                "test_plotting_mpl",
                "0"
              ],
              [
                "test_set_function",
                "2"
              ],
              [
                "test_dummy_cal_three_qubit_graph",
                "2"
              ]
            ]
          },
          {
            "name": "ObscureInLineSetup",
            "hasSmell": false,
            "detail": [
              [
                "test_bad_node",
                [
                  "cal_True_delayed",
                  "cal_False",
                  "test_graph"
                ]
              ],
              [
                "test_write_read_yaml",
                [
                  "read_testgraph",
                  "fn"
                ]
              ],
              [
                "test_calibration_state",
                [
                  "s"
                ]
              ],
              [
                "test_default_not_implemented_cal",
                [
                  "test_graph"
                ]
              ],
              [
                "test_tolerance_check",
                []
              ],
              [
                "test_adding_edge_nonexistent_node",
                [
                  "test_graph"
                ]
              ],
              [
                "test_plotting_svg",
                []
              ],
              [
                "test_maintain_node_assume_unkown_is_good",
                []
              ],
              [
                "test_maintain_node_require_cal",
                []
              ],
              [
                "test_plotting_mpl",
                []
              ],
              [
                "test_set_function",
                []
              ],
              [
                "test_dummy_cal_three_qubit_graph",
                [
                  "fn",
                  "DAG"
                ]
              ]
            ]
          },
          {
            "name": "TestMaverick",
            "hasSmell": true,
            "detail": [
              [
                "test_bad_node",
                []
              ],
              [
                "test_write_read_yaml",
                [
                  "self.test_graph"
                ]
              ],
              [
                "test_calibration_state",
                [
                  "self.test_graph"
                ]
              ],
              [
                "test_default_not_implemented_cal",
                []
              ],
              [
                "test_tolerance_check",
                [
                  "self.test_graph"
                ]
              ],
              [
                "test_adding_edge_nonexistent_node",
                []
              ],
              [
                "test_plotting_svg",
                [
                  "self.test_graph"
                ]
              ],
              [
                "test_maintain_node_assume_unkown_is_good",
                [
                  "self.test_graph"
                ]
              ],
              [
                "test_maintain_node_require_cal",
                [
                  "self.test_graph"
                ]
              ],
              [
                "test_plotting_mpl",
                [
                  "self.test_graph"
                ]
              ],
              [
                "test_set_function",
                [
                  "self.test_graph"
                ]
              ],
              [
                "test_dummy_cal_three_qubit_graph",
                []
              ]
            ]
          },
          {
            "name": "LackCohesion",
            "hasSmell": true,
            "detail": {
              "testClassCohesionScore": 0.2943332185278444,
              "threshold": 0.6,
              "cosineSimilarityScores": [
                [
                  "test_default_not_implemented_cal",
                  "test_calibration_state",
                  0.19444444444444445
                ],
                [
                  "test_maintain_node_assume_unkown_is_good",
                  "test_maintain_node_require_cal",
                  0.7895319219244431
                ],
                [
                  "test_maintain_node_assume_unkown_is_good",
                  "test_adding_edge_nonexistent_node",
                  0.18540496217739155
                ],
                [
                  "test_default_not_implemented_cal",
                  "test_dummy_cal_three_qubit_graph",
                  0.2986595567936803
                ],
                [
                  "test_tolerance_check",
                  "test_plotting_svg",
                  0.1855374339493653
                ],
                [
                  "test_maintain_node_require_cal",
                  "test_adding_edge_nonexistent_node",
                  0.1774341043905996
                ],
                [
                  "test_default_not_implemented_cal",
                  "test_tolerance_check",
                  0.39337931913763496
                ],
                [
                  "test_maintain_node_require_cal",
                  "test_dummy_cal_three_qubit_graph",
                  0.28051474932731063
                ],
                [
                  "test_set_function",
                  "test_dummy_cal_three_qubit_graph",
                  0.37133776793067774
                ],
                [
                  "test_maintain_node_assume_unkown_is_good",
                  "test_plotting_mpl",
                  0.21926450482675733
                ],
                [
                  "test_calibration_state",
                  "test_dummy_cal_three_qubit_graph",
                  0.13176156917368248
                ],
                [
                  "test_set_function",
                  "test_bad_node",
                  0.3442966735191077
                ],
                [
                  "test_default_not_implemented_cal",
                  "test_write_read_yaml",
                  0.44671355618241454
                ],
                [
                  "test_tolerance_check",
                  "test_adding_edge_nonexistent_node",
                  0.2852475199970899
                ],
                [
                  "test_tolerance_check",
                  "test_set_function",
                  0.3848183815246095
                ],
                [
                  "test_maintain_node_assume_unkown_is_good",
                  "test_calibration_state",
                  0.18257418583505536
                ],
                [
                  "test_tolerance_check",
                  "test_maintain_node_require_cal",
                  0.3711593470957042
                ],
                [
                  "test_plotting_mpl",
                  "test_write_read_yaml",
                  0.23176179118107218
                ],
                [
                  "test_tolerance_check",
                  "test_plotting_mpl",
                  0.1855374339493653
                ],
                [
                  "test_set_function",
                  "test_write_read_yaml",
                  0.22317802113732874
                ],
                [
                  "test_default_not_implemented_cal",
                  "test_bad_node",
                  0.637076159105794
                ],
                [
                  "test_default_not_implemented_cal",
                  "test_maintain_node_assume_unkown_is_good",
                  0.36514837167011066
                ],
                [
                  "test_default_not_implemented_cal",
                  "test_maintain_node_require_cal",
                  0.3572902809613768
                ],
                [
                  "test_default_not_implemented_cal",
                  "test_adding_edge_nonexistent_node",
                  0.7180336973794409
                ],
                [
                  "test_default_not_implemented_cal",
                  "test_plotting_mpl",
                  0.09340808971963417
                ],
                [
                  "test_calibration_state",
                  "test_write_read_yaml",
                  0.2680281337094487
                ],
                [
                  "test_calibration_state",
                  "test_plotting_svg",
                  0.28022426915890253
                ],
                [
                  "test_maintain_node_assume_unkown_is_good",
                  "test_plotting_svg",
                  0.21926450482675733
                ],
                [
                  "test_calibration_state",
                  "test_bad_node",
                  0.22894924467864472
                ],
                [
                  "test_set_function",
                  "test_maintain_node_require_cal",
                  0.37878443958849867
                ],
                [
                  "test_maintain_node_require_cal",
                  "test_write_read_yaml",
                  0.32097399819669503
                ],
                [
                  "test_set_function",
                  "test_adding_edge_nonexistent_node",
                  0.2562353715952691
                ],
                [
                  "test_maintain_node_assume_unkown_is_good",
                  "test_set_function",
                  0.40929374234328025
                ],
                [
                  "test_tolerance_check",
                  "test_dummy_cal_three_qubit_graph",
                  0.48854276491334026
                ],
                [
                  "test_maintain_node_require_cal",
                  "test_plotting_mpl",
                  0.17755520605710878
                ],
                [
                  "test_maintain_node_assume_unkown_is_good",
                  "test_dummy_cal_three_qubit_graph",
                  0.21650635094610965
                ],
                [
                  "test_plotting_svg",
                  "test_write_read_yaml",
                  0.23176179118107218
                ],
                [
                  "test_calibration_state",
                  "test_set_function",
                  0.10675210253672475
                ],
                [
                  "test_maintain_node_assume_unkown_is_good",
                  "test_write_read_yaml",
                  0.33765162622095446
                ],
                [
                  "test_tolerance_check",
                  "test_write_read_yaml",
                  0.4071774606645523
                ],
                [
                  "test_set_function",
                  "test_plotting_mpl",
                  0.1282051282051282
                ],
                [
                  "test_maintain_node_assume_unkown_is_good",
                  "test_bad_node",
                  0.33258437460391577
                ],
                [
                  "test_tolerance_check",
                  "test_maintain_node_assume_unkown_is_good",
                  0.28206029683336103
                ],
                [
                  "test_bad_node",
                  "test_plotting_svg",
                  0.11476555783970259
                ],
                [
                  "test_default_not_implemented_cal",
                  "test_set_function",
                  0.26688025634181184
                ],
                [
                  "test_plotting_mpl",
                  "test_adding_edge_nonexistent_node",
                  0.10347966929808945
                ],
                [
                  "test_plotting_svg",
                  "test_dummy_cal_three_qubit_graph",
                  0.1139331787969125
                ],
                [
                  "test_tolerance_check",
                  "test_bad_node",
                  0.45366573753706363
                ],
                [
                  "test_set_function",
                  "test_plotting_svg",
                  0.1282051282051282
                ],
                [
                  "test_bad_node",
                  "test_plotting_mpl",
                  0.11476555783970259
                ],
                [
                  "test_bad_node",
                  "test_adding_edge_nonexistent_node",
                  0.635926274646907
                ],
                [
                  "test_default_not_implemented_cal",
                  "test_plotting_svg",
                  0.09340808971963417
                ],
                [
                  "test_write_read_yaml",
                  "test_adding_edge_nonexistent_node",
                  0.35631341210920314
                ],
                [
                  "test_tolerance_check",
                  "test_calibration_state",
                  0.17165643016914983
                ],
                [
                  "test_dummy_cal_three_qubit_graph",
                  "test_adding_edge_nonexistent_node",
                  0.23354968324845687
                ],
                [
                  "test_maintain_node_require_cal",
                  "test_bad_node",
                  0.31346960259433154
                ],
                [
                  "test_plotting_mpl",
                  "test_dummy_cal_three_qubit_graph",
                  0.1139331787969125
                ],
                [
                  "test_maintain_node_require_cal",
                  "test_plotting_svg",
                  0.17755520605710878
                ],
                [
                  "test_dummy_cal_three_qubit_graph",
                  "test_write_read_yaml",
                  0.37293492699144576
                ],
                [
                  "test_plotting_svg",
                  "test_adding_edge_nonexistent_node",
                  0.10347966929808945
                ],
                [
                  "test_calibration_state",
                  "test_maintain_node_require_cal",
                  0.1478442541909146
                ],
                [
                  "test_calibration_state",
                  "test_adding_edge_nonexistent_node",
                  0.21541010921383227
                ],
                [
                  "test_plotting_mpl",
                  "test_plotting_svg",
                  0.9423076923076924
                ],
                [
                  "test_bad_node",
                  "test_dummy_cal_three_qubit_graph",
                  0.38718318720192774
                ],
                [
                  "test_calibration_state",
                  "test_plotting_mpl",
                  0.28022426915890253
                ],
                [
                  "test_bad_node",
                  "test_write_read_yaml",
                  0.4610367016809564
                ]
              ]
            }
          },
          {
            "name": "SuboptimalAssert",
            "hasSmell": false,
            "detail": [
              [
                "test_bad_node",
                "false"
              ],
              [
                "test_write_read_yaml",
                "false"
              ],
              [
                "test_calibration_state",
                "false"
              ],
              [
                "test_default_not_implemented_cal",
                "false"
              ],
              [
                "test_tolerance_check",
                "false"
              ],
              [
                "test_adding_edge_nonexistent_node",
                "false"
              ],
              [
                "test_plotting_svg",
                "false"
              ],
              [
                "test_maintain_node_assume_unkown_is_good",
                "false"
              ],
              [
                "test_maintain_node_require_cal",
                "false"
              ],
              [
                "test_plotting_mpl",
                "false"
              ],
              [
                "test_set_function",
                "false"
              ],
              [
                "test_dummy_cal_three_qubit_graph",
                "false"
              ]
            ]
          }
        ],
        "numberOfMethods": 12
      }
    ]
  }
]