[
  {
    "name": "AppImageBuilder_\u0026_app_dir_\u0026_runtimes_\u0026_wrapper_\u0026_test_app_run.py",
    "testCases": [
      {
        "name": "AppRunTestCase",
        "detectorResults": [
          {
            "name": "AssertionRoulette",
            "hasSmell": false,
            "detail": {
              "assertionCallsInTests": [
                [
                  "test_minimal_script_generation",
                  "[PyCallExpression: self.assertEqual]"
                ]
              ],
              "assertStatementsInTests": [
                [
                  "test_minimal_script_generation",
                  "[]"
                ]
              ]
            }
          },
          {
            "name": "ConditionalTestLogic",
            "hasSmell": false,
            "detail": {
              "testHasConditionalTestLogic": [
                [
                  "test_minimal_script_generation",
                  "false"
                ]
              ],
              "testHasComprehension": [
                [
                  "test_minimal_script_generation",
                  "false"
                ]
              ]
            }
          },
          {
            "name": "ConstructorInitialization",
            "hasSmell": false
          },
          {
            "name": "DefaultTest",
            "hasSmell": false
          },
          {
            "name": "DuplicateAssertion",
            "hasSmell": false,
            "detail": {
              "testHasDuplicateAssertCall": [
                [
                  "test_minimal_script_generation",
                  "false"
                ]
              ],
              "testHasDuplicateAssertStatement": [
                [
                  "test_minimal_script_generation",
                  "false"
                ]
              ]
            }
          },
          {
            "name": "EmptyTest",
            "hasSmell": false,
            "detail": [
              [
                "test_minimal_script_generation",
                "false"
              ]
            ]
          },
          {
            "name": "ExceptionHandling",
            "hasSmell": false,
            "detail": [
              [
                "test_minimal_script_generation",
                "false"
              ]
            ]
          },
          {
            "name": "GeneralFixture",
            "hasSmell": false,
            "detail": [
              [
                "test_minimal_script_generation",
                []
              ]
            ]
          },
          {
            "name": "IgnoredTest",
            "hasSmell": false,
            "detail": [
              [
                "test_minimal_script_generation",
                "false"
              ]
            ]
          },
          {
            "name": "MagicNumberTest",
            "hasSmell": false,
            "detail": [
              [
                "test_minimal_script_generation",
                "false"
              ]
            ]
          },
          {
            "name": "RedundantAssertion",
            "hasSmell": false,
            "detail": {
              "testMethodHaveRedundantAssertCall": [
                [
                  "test_minimal_script_generation",
                  "0"
                ]
              ],
              "testMethodHaveRedundantAssertStatement": [
                [
                  "test_minimal_script_generation",
                  "0"
                ]
              ]
            }
          },
          {
            "name": "RedundantPrint",
            "hasSmell": false,
            "detail": [
              [
                "test_minimal_script_generation",
                "false"
              ]
            ]
          },
          {
            "name": "SleepyTest",
            "hasSmell": false,
            "detail": [
              [
                "test_minimal_script_generation",
                "false"
              ]
            ]
          },
          {
            "name": "UnknownTest",
            "hasSmell": false,
            "detail": [
              [
                "test_minimal_script_generation",
                "1"
              ]
            ]
          },
          {
            "name": "ObscureInLineSetup",
            "hasSmell": false,
            "detail": [
              [
                "test_minimal_script_generation",
                [
                  "lines",
                  "app_run"
                ]
              ]
            ]
          },
          {
            "name": "TestMaverick",
            "hasSmell": false,
            "detail": [
              [
                "test_minimal_script_generation",
                []
              ]
            ]
          },
          {
            "name": "LackCohesion",
            "hasSmell": false,
            "detail": {
              "testClassCohesionScore": 0.0,
              "threshold": 0.6,
              "cosineSimilarityScores": []
            }
          },
          {
            "name": "SuboptimalAssert",
            "hasSmell": false,
            "detail": [
              [
                "test_minimal_script_generation",
                "false"
              ]
            ]
          }
        ],
        "numberOfMethods": 1
      }
    ]
  },
  {
    "name": "AppImageBuilder_\u0026_app_dir_\u0026_runtimes_\u0026_classic_\u0026_helpers_\u0026_test_dynamic_loader.py",
    "testCases": [
      {
        "name": "DynamicLoaderTestCase",
        "detectorResults": [
          {
            "name": "AssertionRoulette",
            "hasSmell": false,
            "detail": {
              "assertionCallsInTests": [
                [
                  "test_list_libs",
                  "[PyCallExpression: self.assertEqual]"
                ],
                [
                  "test_get_binary_path",
                  "[PyCallExpression: self.assertEqual]"
                ]
              ],
              "assertStatementsInTests": [
                [
                  "test_list_libs",
                  "[]"
                ],
                [
                  "test_get_binary_path",
                  "[]"
                ]
              ]
            }
          },
          {
            "name": "ConditionalTestLogic",
            "hasSmell": false,
            "detail": {
              "testHasConditionalTestLogic": [
                [
                  "test_list_libs",
                  "false"
                ],
                [
                  "test_get_binary_path",
                  "false"
                ]
              ],
              "testHasComprehension": [
                [
                  "test_list_libs",
                  "false"
                ],
                [
                  "test_get_binary_path",
                  "false"
                ]
              ]
            }
          },
          {
            "name": "ConstructorInitialization",
            "hasSmell": false
          },
          {
            "name": "DefaultTest",
            "hasSmell": false
          },
          {
            "name": "DuplicateAssertion",
            "hasSmell": false,
            "detail": {
              "testHasDuplicateAssertCall": [
                [
                  "test_list_libs",
                  "false"
                ],
                [
                  "test_get_binary_path",
                  "false"
                ]
              ],
              "testHasDuplicateAssertStatement": [
                [
                  "test_list_libs",
                  "false"
                ],
                [
                  "test_get_binary_path",
                  "false"
                ]
              ]
            }
          },
          {
            "name": "EmptyTest",
            "hasSmell": false,
            "detail": [
              [
                "test_list_libs",
                "false"
              ],
              [
                "test_get_binary_path",
                "false"
              ]
            ]
          },
          {
            "name": "ExceptionHandling",
            "hasSmell": false,
            "detail": [
              [
                "test_list_libs",
                "false"
              ],
              [
                "test_get_binary_path",
                "false"
              ]
            ]
          },
          {
            "name": "GeneralFixture",
            "hasSmell": true,
            "detail": [
              [
                "test_list_libs",
                [
                  "self.app_dir_files"
                ]
              ],
              [
                "test_get_binary_path",
                []
              ]
            ]
          },
          {
            "name": "IgnoredTest",
            "hasSmell": false,
            "detail": [
              [
                "test_list_libs",
                "false"
              ],
              [
                "test_get_binary_path",
                "false"
              ]
            ]
          },
          {
            "name": "MagicNumberTest",
            "hasSmell": false,
            "detail": [
              [
                "test_list_libs",
                "false"
              ],
              [
                "test_get_binary_path",
                "false"
              ]
            ]
          },
          {
            "name": "RedundantAssertion",
            "hasSmell": false,
            "detail": {
              "testMethodHaveRedundantAssertCall": [
                [
                  "test_list_libs",
                  "0"
                ],
                [
                  "test_get_binary_path",
                  "0"
                ]
              ],
              "testMethodHaveRedundantAssertStatement": [
                [
                  "test_list_libs",
                  "0"
                ],
                [
                  "test_get_binary_path",
                  "0"
                ]
              ]
            }
          },
          {
            "name": "RedundantPrint",
            "hasSmell": false,
            "detail": [
              [
                "test_list_libs",
                "false"
              ],
              [
                "test_get_binary_path",
                "false"
              ]
            ]
          },
          {
            "name": "SleepyTest",
            "hasSmell": false,
            "detail": [
              [
                "test_list_libs",
                "false"
              ],
              [
                "test_get_binary_path",
                "false"
              ]
            ]
          },
          {
            "name": "UnknownTest",
            "hasSmell": false,
            "detail": [
              [
                "test_list_libs",
                "1"
              ],
              [
                "test_get_binary_path",
                "1"
              ]
            ]
          },
          {
            "name": "ObscureInLineSetup",
            "hasSmell": false,
            "detail": [
              [
                "test_list_libs",
                [
                  "dl"
                ]
              ],
              [
                "test_get_binary_path",
                [
                  "dl"
                ]
              ]
            ]
          },
          {
            "name": "TestMaverick",
            "hasSmell": true,
            "detail": [
              [
                "test_list_libs",
                []
              ],
              [
                "test_get_binary_path",
                [
                  "self.app_dir_files"
                ]
              ]
            ]
          },
          {
            "name": "LackCohesion",
            "hasSmell": true,
            "detail": {
              "testClassCohesionScore": 0.3162277660168379,
              "threshold": 0.6,
              "cosineSimilarityScores": [
                [
                  "test_get_binary_path",
                  "test_list_libs",
                  0.3162277660168379
                ]
              ]
            }
          },
          {
            "name": "SuboptimalAssert",
            "hasSmell": false,
            "detail": [
              [
                "test_list_libs",
                "false"
              ],
              [
                "test_get_binary_path",
                "false"
              ]
            ]
          }
        ],
        "numberOfMethods": 2
      }
    ]
  },
  {
    "name": "AppImageBuilder_\u0026_app_dir_\u0026_runtimes_\u0026_wrapper_\u0026_helpers_\u0026_test_dynamic_loader.py",
    "testCases": [
      {
        "name": "DynamicLoaderTestCase",
        "detectorResults": [
          {
            "name": "AssertionRoulette",
            "hasSmell": false,
            "detail": {
              "assertionCallsInTests": [
                [
                  "test_get_binary_path",
                  "[PyCallExpression: self.assertEqual]"
                ],
                [
                  "test_list_libs",
                  "[PyCallExpression: self.assertEqual]"
                ]
              ],
              "assertStatementsInTests": [
                [
                  "test_get_binary_path",
                  "[]"
                ],
                [
                  "test_list_libs",
                  "[]"
                ]
              ]
            }
          },
          {
            "name": "ConditionalTestLogic",
            "hasSmell": false,
            "detail": {
              "testHasConditionalTestLogic": [
                [
                  "test_get_binary_path",
                  "false"
                ],
                [
                  "test_list_libs",
                  "false"
                ]
              ],
              "testHasComprehension": [
                [
                  "test_get_binary_path",
                  "false"
                ],
                [
                  "test_list_libs",
                  "false"
                ]
              ]
            }
          },
          {
            "name": "ConstructorInitialization",
            "hasSmell": false
          },
          {
            "name": "DefaultTest",
            "hasSmell": false
          },
          {
            "name": "DuplicateAssertion",
            "hasSmell": false,
            "detail": {
              "testHasDuplicateAssertCall": [
                [
                  "test_get_binary_path",
                  "false"
                ],
                [
                  "test_list_libs",
                  "false"
                ]
              ],
              "testHasDuplicateAssertStatement": [
                [
                  "test_get_binary_path",
                  "false"
                ],
                [
                  "test_list_libs",
                  "false"
                ]
              ]
            }
          },
          {
            "name": "EmptyTest",
            "hasSmell": false,
            "detail": [
              [
                "test_get_binary_path",
                "false"
              ],
              [
                "test_list_libs",
                "false"
              ]
            ]
          },
          {
            "name": "ExceptionHandling",
            "hasSmell": false,
            "detail": [
              [
                "test_get_binary_path",
                "false"
              ],
              [
                "test_list_libs",
                "false"
              ]
            ]
          },
          {
            "name": "GeneralFixture",
            "hasSmell": true,
            "detail": [
              [
                "test_get_binary_path",
                []
              ],
              [
                "test_list_libs",
                [
                  "self.app_dir_files"
                ]
              ]
            ]
          },
          {
            "name": "IgnoredTest",
            "hasSmell": false,
            "detail": [
              [
                "test_get_binary_path",
                "false"
              ],
              [
                "test_list_libs",
                "false"
              ]
            ]
          },
          {
            "name": "MagicNumberTest",
            "hasSmell": false,
            "detail": [
              [
                "test_get_binary_path",
                "false"
              ],
              [
                "test_list_libs",
                "false"
              ]
            ]
          },
          {
            "name": "RedundantAssertion",
            "hasSmell": false,
            "detail": {
              "testMethodHaveRedundantAssertCall": [
                [
                  "test_get_binary_path",
                  "0"
                ],
                [
                  "test_list_libs",
                  "0"
                ]
              ],
              "testMethodHaveRedundantAssertStatement": [
                [
                  "test_get_binary_path",
                  "0"
                ],
                [
                  "test_list_libs",
                  "0"
                ]
              ]
            }
          },
          {
            "name": "RedundantPrint",
            "hasSmell": false,
            "detail": [
              [
                "test_get_binary_path",
                "false"
              ],
              [
                "test_list_libs",
                "false"
              ]
            ]
          },
          {
            "name": "SleepyTest",
            "hasSmell": false,
            "detail": [
              [
                "test_get_binary_path",
                "false"
              ],
              [
                "test_list_libs",
                "false"
              ]
            ]
          },
          {
            "name": "UnknownTest",
            "hasSmell": false,
            "detail": [
              [
                "test_get_binary_path",
                "1"
              ],
              [
                "test_list_libs",
                "1"
              ]
            ]
          },
          {
            "name": "ObscureInLineSetup",
            "hasSmell": false,
            "detail": [
              [
                "test_get_binary_path",
                [
                  "dl"
                ]
              ],
              [
                "test_list_libs",
                [
                  "dl"
                ]
              ]
            ]
          },
          {
            "name": "TestMaverick",
            "hasSmell": true,
            "detail": [
              [
                "test_get_binary_path",
                [
                  "self.app_dir_files"
                ]
              ],
              [
                "test_list_libs",
                []
              ]
            ]
          },
          {
            "name": "LackCohesion",
            "hasSmell": true,
            "detail": {
              "testClassCohesionScore": 0.3162277660168379,
              "threshold": 0.6,
              "cosineSimilarityScores": [
                [
                  "test_get_binary_path",
                  "test_list_libs",
                  0.3162277660168379
                ]
              ]
            }
          },
          {
            "name": "SuboptimalAssert",
            "hasSmell": false,
            "detail": [
              [
                "test_get_binary_path",
                "false"
              ],
              [
                "test_list_libs",
                "false"
              ]
            ]
          }
        ],
        "numberOfMethods": 2
      }
    ]
  }
]